{
  "date": "2026-07-02",
  "weekday": "週四",
  "editor": "熊誠毅",
  "kpis": [
    { "name": "加權指數", "value": "47,018", "chg": "+893 (+1.94%)", "dir": "up", "note": "帶量重返47K" },
    { "name": "美元/台幣", "value": "31.874", "chg": "貶值", "dir": "down", "note": "近三月新低" },
    { "name": "日圓/美元", "value": "162.84", "chg": "貶值", "dir": "down", "note": "40年新低" },
    { "name": "台積電", "value": "2,505", "chg": "+95 (+3.94%)", "dir": "up", "note": "歷史次高" }
  ],
  "focus": [
    { "title": "台股帶量重返 47K", "market": "股市", "tag": "偏多", "take": "台積電領軍、外資終止連六賣轉買，但買盤集中電子、漲多股留意獲利了結。" },
    { "title": "日圓破底，官方傳7/3干預", "market": "匯率", "tag": "偏空", "take": "美日利差是主因，干預頂多減緩跌勢、難改長期趨勢；留意美債連動。" },
    { "title": "日企短觀信心8年最高", "market": "日股", "tag": "中性", "take": "信心與通膨預期雙升，強化日銀升息可能，何時升息成焦點。" },
    { "title": "7月升息？Fed華許拒透露", "market": "美股", "tag": "中性", "take": "不給前瞻指引＋就業放緩，市場不確定性升高，波動可能加大。" }
  ],
  "clientLine": "行情熱的時候，正是把一部分獲利『鎖成確定性』的好時機。"
}
